MANIFEST.in
README.md
setup.cfg
setup.py
versioneer.py
ktpl/__init__.py
ktpl/_version.py
ktpl/cli.py
ktpl/filters.py
ktpl/kube.py
ktpl.egg-info/PKG-INFO
ktpl.egg-info/SOURCES.txt
ktpl.egg-info/dependency_links.txt
ktpl.egg-info/entry_points.txt
ktpl.egg-info/requires.txt
ktpl.egg-info/top_level.txt