Metadata-Version: 1.1
Name: ktpl
Version: 0.0.16
Summary: Utility to template Kubernetes Resource Definitions using the jinja2 templating language
Home-page: https://github.com/whereismyjetpack/ktpl
Author: Dann Bohn
Author-email: dannbohn@gmail.com
License: ISC
Platform: UNKNOWN
Classifier: License :: OSI Approved :: MIT License
Classifier: Intended Audience :: System Administrators
Classifier: Intended Audience :: Developers
Classifier: Natural Language :: English
Classifier: Topic :: Software Development :: Build Tools
Classifier: Topic :: Utilities
Classifier: Programming Language :: Python
Classifier: Programming Language :: Python :: 3.5
Classifier: Programming Language :: Python :: 3.6
Classifier: Programming Language :: Python :: 2.7
Classifier: Programming Language :: Python :: Implementation :: CPython
